import{_ as s,o as a,c as n,a as l}from"./app.5f974767.js";const y=JSON.parse('{"title":"ClassLoader\u2014\u2014\u7C7B\u52A0\u8F7D\u5668","description":"","frontmatter":{"tittle":"ClassLoader\u2014\u2014\u7C7B\u52A0\u8F7D\u5668","date":"2023/03/11","tags":["Java","JVM\u5E95\u5C42\u539F\u7406"]},"headers":[{"level":2,"title":"class\u6587\u4EF6\u53CAClass\u5BF9\u8C61\u7B80\u8FF0","slug":"class\u6587\u4EF6\u53CAclass\u5BF9\u8C61\u7B80\u8FF0","link":"#class\u6587\u4EF6\u53CAclass\u5BF9\u8C61\u7B80\u8FF0","children":[]},{"level":2,"title":"\u7C7B\u52A0\u8F7D\u5668","slug":"\u7C7B\u52A0\u8F7D\u5668","link":"#\u7C7B\u52A0\u8F7D\u5668","children":[{"level":3,"title":"BootstrapClassLoader\u2014\u2014\u5F15\u5BFC\u7C7B\u52A0\u8F7D\u5668","slug":"bootstrapclassloader\u2014\u2014\u5F15\u5BFC\u7C7B\u52A0\u8F7D\u5668","link":"#bootstrapclassloader\u2014\u2014\u5F15\u5BFC\u7C7B\u52A0\u8F7D\u5668","children":[]},{"level":3,"title":"ExtensionClassLoader\u2014\u2014\u6269\u5C55\u7C7B\u52A0\u8F7D\u5668","slug":"extensionclassloader\u2014\u2014\u6269\u5C55\u7C7B\u52A0\u8F7D\u5668","link":"#extensionclassloader\u2014\u2014\u6269\u5C55\u7C7B\u52A0\u8F7D\u5668","children":[]},{"level":3,"title":"SystemClassLoader\u2014\u2014\u7CFB\u7EDF\u7C7B\u52A0\u8F7D\u5668","slug":"systemclassloader\u2014\u2014\u7CFB\u7EDF\u7C7B\u52A0\u8F7D\u5668","link":"#systemclassloader\u2014\u2014\u7CFB\u7EDF\u7C7B\u52A0\u8F7D\u5668","children":[]},{"level":3,"title":"CustomClassLoader\u2014\u2014\u81EA\u5B9A\u7C7B\u52A0\u8F7D\u5668","slug":"customclassloader\u2014\u2014\u81EA\u5B9A\u7C7B\u52A0\u8F7D\u5668","link":"#customclassloader\u2014\u2014\u81EA\u5B9A\u7C7B\u52A0\u8F7D\u5668","children":[]}]},{"level":2,"title":"CLASSPATH","slug":"classpath","link":"#classpath","children":[{"level":3,"title":"jar\u5305","slug":"jar\u5305","link":"#jar\u5305","children":[]}]},{"level":2,"title":"\u53CC\u4EB2\u59D4\u6D3E\u673A\u5236\uFF08parent-\uFF09","slug":"\u53CC\u4EB2\u59D4\u6D3E\u673A\u5236\uFF08parent-\uFF09","link":"#\u53CC\u4EB2\u59D4\u6D3E\u673A\u5236\uFF08parent-\uFF09","children":[{"level":3,"title":"\u7F3A\u9677","slug":"\u7F3A\u9677","link":"#\u7F3A\u9677","children":[]}]},{"level":2,"title":"\u5E38\u91CF\u6C60","slug":"\u5E38\u91CF\u6C60","link":"#\u5E38\u91CF\u6C60","children":[]}],"relativePath":"Java/JVM\u5E95\u5C42\u539F\u7406/Class\u5BF9\u8C61\u53CAClassLoader.md"}'),p={name:"Java/JVM\u5E95\u5C42\u539F\u7406/Class\u5BF9\u8C61\u53CAClassLoader.md"},e=l(`<h1 id="classloader\u2014\u2014\u7C7B\u52A0\u8F7D\u5668" tabindex="-1">ClassLoader\u2014\u2014\u7C7B\u52A0\u8F7D\u5668 <a class="header-anchor" href="#classloader\u2014\u2014\u7C7B\u52A0\u8F7D\u5668" aria-hidden="true">#</a></h1><h2 id="class\u6587\u4EF6\u53CAclass\u5BF9\u8C61\u7B80\u8FF0" tabindex="-1">class\u6587\u4EF6\u53CAClass\u5BF9\u8C61\u7B80\u8FF0 <a class="header-anchor" href="#class\u6587\u4EF6\u53CAclass\u5BF9\u8C61\u7B80\u8FF0" aria-hidden="true">#</a></h2><hr><p>\u5F53\u6211\u4EEC\u7F16\u8BD1\u5E76\u6267\u884C\u4E00\u4E2AJava\u7A0B\u5E8F\u65F6\uFF0C\u5B9E\u9645\u4E0A\u7ECF\u8FC7\u4E86\u591A\u6B65\uFF1A</p><ol><li>\u7F16\u8BD1\uFF1A.java\u6E90\u7801\u6587\u4EF6\u7531\u7F16\u8BD1\u5668\u7F16\u8BD1\u4E3A.class\u5B57\u8282\u7801\u6587\u4EF6</li><li>\u6267\u884C\uFF1Aclass\u5B57\u8282\u7801\u5728\u88ABJVM\u865A\u62DF\u673A\u6267\u884C\u65F6\u7531\u76F8\u5E94\u7684classLoader\u52A0\u8F7D\u8FDB\u5185\u5B58\uFF0C\u521B\u5EFA\u4E3AClass\u5BF9\u8C61</li><li>\u5B9E\u4F8B\u5316\uFF1AJVM\u6839\u636EClass\u5BF9\u8C61\u5B9E\u4F8B\u5316\u4E00\u4E2A\u65B0\u7684\u5BF9\u8C61\u4EE5\u4F9B\u8FDB\u7A0B\u8C03\u7528</li></ol><p>\u5728Java\u4E2D\uFF0C\u4E00\u4E2A\u7C7B<strong>\u4E25\u683C\u5BF9\u5E94</strong>\u4E00\u4E2Aclass\u6587\u4EF6\uFF0C\u6BCF\u4E2Aclass\u6587\u4EF6\u63CF\u8FF0\u4E86\u5173\u4E8E\u8FD9\u4E2A\u7C7B\u7684\u8BE6\u7EC6\u4FE1\u606F\uFF0C\u5305\u62EC\u5176\u5143\u6570\u636E\u3001\u5E38\u91CF\u6C60\u3001\u6784\u9020\u65B9\u6CD5\u3001\u6210\u5458\u53D8\u91CF\u3001\u6210\u5458\u65B9\u6CD5\u3001\u9759\u6001\u6210\u5458\u7B49\u5185\u5BB9\u3002</p><p>\u6211\u4EEC\u53EF\u4EE5\u8BA4\u4E3A\uFF0CJVM\u4E2D\u5B58\u5728\u4E24\u79CD\u5BF9\u8C61\u2014\u2014\u5B9E\u4F8B\u5BF9\u8C61\u548CClass\u5BF9\u8C61\uFF0CClass\u5BF9\u8C61\u662F\u5BF9\u5E94\u5B9E\u4F8B\u5BF9\u8C61\u7684\u4E00\u4E2A<strong>\u9759\u6001\u84DD\u56FE</strong>\uFF0C\u5728\u9996\u6B21\u5B9E\u4F8B\u5316\u4E00\u4E2A\u5BF9\u8C61\u65F6\uFF0C\u6211\u4EEC\u4F1A\u5148\u52A0\u8F7D\u5E76\u521B\u5EFA\u4E00\u4E2AClass\u5BF9\u8C61\uFF0C\u7136\u540E\u4EE5\u8BE5Class\u5BF9\u8C61\u4E3A\u84DD\u56FE\u6784\u5EFA\u5B9E\u4F8B\u5BF9\u8C61\uFF0C\u6B64\u540E\u6BCF\u6B21\u5B9E\u4F8B\u5316\u65B0\u7684\u540C\u7C7B\u5BF9\u8C61\u90FD\u4F1A\u8C03\u7528\u8BE5Class\u5BF9\u8C61\u3002</p><h2 id="\u7C7B\u52A0\u8F7D\u5668" tabindex="-1">\u7C7B\u52A0\u8F7D\u5668 <a class="header-anchor" href="#\u7C7B\u52A0\u8F7D\u5668" aria-hidden="true">#</a></h2><hr><p>Class\u5BF9\u8C61\u7684\u6784\u9020\u51FD\u6570\u662F<strong>\u79C1\u6709\u7684</strong>\uFF0C\u65E0\u6CD5\u5728\u5916\u90E8\u8FDB\u884C\u663E\u5F0F\u8C03\u7528\uFF0C\u4E5F\u65E0\u6CD5\u663E\u5F0F\u58F0\u660E\u4E00\u4E2AClass\u5BF9\u8C61\u3002</p><p>\u4F46\u662F\u6BCF\u4E2AClass\u5BF9\u8C61\u90FD\u6709\u4E00\u4E2AclassLoader\u5B57\u6BB5\u7ED1\u5B9A\u6784\u9020\u81EA\u5DF1\u7684\u7C7B\u52A0\u8F7D\u5668\uFF0C\u5728\u5B9E\u9645\u52A0\u8F7D\u65F6\u901A\u8FC7classLoader\u7684defineClass\u65B9\u6CD5\u6784\u9020\u81EA\u8EAB</p><p>\u5F53\u6211\u4EEC\u9996\u6B21\u8C03\u7528\u4E00\u4E2A\u7C7B\u65F6\uFF0CJVM\u901A\u8FC7classLoader\u5BFB\u627E\u5E76\u52A0\u8F7D\u76F8\u5E94\u7684class\u6587\u4EF6\uFF0C\u521B\u5EFA\u4E00\u4E2A\u5BF9\u5E94\u7684Class\u5BF9\u8C61\uFF08\u8FD9\u79CD<strong>\u6309\u9700\u52A0\u8F7D</strong>\u7684\u65B9\u5F0F\u4E5F\u88AB\u53EB\u505A<strong>\u61D2\u52A0\u8F7D</strong>/<strong>\u52A8\u6001\u52A0\u8F7D</strong>\uFF09\u3002\u6BCF\u6B21\u5F53\u6211\u4EEC\u901A\u8FC7new\u5B9E\u4F8B\u5316\u4E00\u4E2A\u65B0\u7684\u5BF9\u8C61\u65F6\uFF0C\u5B9E\u9645\u4E0A\u5728JVM\u773C\u4E2D\u662F\u901A\u8FC7\u52A8\u6001\u52A0\u8F7D\u5165\u5185\u5B58\u7684Class\u5BF9\u8C61\u8C03\u7528\u76F8\u5E94\u7684\u6784\u9020\u5668\u5E76\u6784\u9020\u4E00\u4E2A\u65B0\u7684\u5BF9\u8C61\uFF0C\u56E0\u6B64Class\u5BF9\u8C61\u53EA\u4F1A\u5728\u9996\u6B21\u8C03\u7528\u65F6\u52A0\u8F7D\u5E76\u7528\u4E8E\u521B\u9020\u6240\u6709\u8BE5Class\u5BF9\u5E94\u7684\u5BF9\u8C61\u3002</p><p>\u6362\u53E5\u8BDD\u8BF4\uFF0C\u5982\u679C\u7A0B\u5E8F\u8FD0\u884C\u65F6\u6CA1\u6709\u771F\u6B63\u8C03\u7528\u5230\u4E00\u4E2A\u5BF9\u8C61\uFF0C\u90A3\u4E48JVM\u5C31\u4E0D\u4F1A\u53BB\u52A0\u8F7D\u8FD9\u4E2AClass\u7C7B\uFF1B\u5B9E\u9645\u4E2D\u6211\u4EEC\u7ECF\u5E38\u901A\u8FC7\u52A8\u6001\u52A0\u8F7D\u7684\u7279\u6027\u6765\u6839\u636E\u7A0B\u5E8F\u7684\u5B9E\u9645\u8FD0\u884C\u72B6\u6001\u6765\u52A0\u8F7D\u4E0D\u540C\u7684\u7C7B\u3002</p><div class="language-java line-numbers-mode"><button title="Copy Code" class="copy"></button><span class="lang">java</span><pre class="shiki"><code><span class="line"><span style="color:#C792EA;">class</span><span style="color:#A6ACCD;"> </span><span style="color:#FFCB6B;">Class</span><span style="color:#89DDFF;">&lt;</span><span style="color:#C792EA;">T</span><span style="color:#89DDFF;">&gt;</span><span style="color:#A6ACCD;"> </span><span style="color:#89DDFF;">{</span></span>
<span class="line"><span style="color:#A6ACCD;">  </span><span style="color:#89DDFF;">...</span></span>
<span class="line"><span style="color:#A6ACCD;">  </span><span style="color:#C792EA;">private</span><span style="color:#A6ACCD;"> </span><span style="color:#C792EA;">final</span><span style="color:#A6ACCD;"> </span><span style="color:#C792EA;">ClassLoader</span><span style="color:#A6ACCD;"> classLoader</span><span style="color:#89DDFF;">;</span></span>
<span class="line"><span style="color:#A6ACCD;">  </span><span style="color:#89DDFF;">...</span></span>
<span class="line"><span style="color:#89DDFF;">}</span></span>
<span class="line"></span></code></pre><div class="line-numbers-wrapper"><span class="line-number">1</span><br><span class="line-number">2</span><br><span class="line-number">3</span><br><span class="line-number">4</span><br><span class="line-number">5</span><br></div></div><p>\u8003\u8651\u5230\u4E0D\u540Cclass\u7684\u6765\u6E90\uFF08java\u6838\u5FC3\u7C7B\u3001\u6269\u5C55\u6846\u67B6\u3001\u9879\u76EE\u81EA\u8EAB\u7C7B\u7B49\u7B49\uFF09\uFF0CJVM\u5728java.lang.ClassLoader\u4E2D\u63D0\u4F9B\u4E86\u591A\u4E2Aclassloader\uFF0C\u5728\u9996\u6B21\u8C03\u7528\u4E00\u4E2A\u65B0\u7C7B\u65F6\uFF0C\u6839\u636E\u4F18\u5148\u7EA7\u9010\u4E2A\u5C1D\u8BD5\u52A0\u8F7D\u3002</p><h3 id="bootstrapclassloader\u2014\u2014\u5F15\u5BFC\u7C7B\u52A0\u8F7D\u5668" tabindex="-1">BootstrapClassLoader\u2014\u2014\u5F15\u5BFC\u7C7B\u52A0\u8F7D\u5668 <a class="header-anchor" href="#bootstrapclassloader\u2014\u2014\u5F15\u5BFC\u7C7B\u52A0\u8F7D\u5668" aria-hidden="true">#</a></h3><p>BootstrapClassLoader\u7528\u4E8E\u52A0\u8F7DJDK\u5185\u90E8\u7684\u6838\u5FC3\u7C7B\uFF08\u5982java.util.*\u3001java.lang.*\u7B49\uFF09\uFF0C\u5B83\u5C5E\u4E8EJVM\u865A\u62DF\u673A\u6838\u5FC3\u7684\u4E00\u90E8\u5206\u3002\u6B64\u5916BootstrapClassLoader\u4E5F\u662F\u5176\u4ED6\u6240\u6709\u7C7B\u52A0\u8F7D\u5668\u7684\u7236\u7C7B\uFF0C\u56E0\u6B64\u4E5F\u88AB\u53EB\u505A<strong>\u6839\u52A0\u8F7D\u5668</strong>\u3002</p><ul><li>BootstrapClassLoader\u52A0\u8F7D\u7684\u7C7B\u4E00\u822C\u5728JAVA_HOME/lib\u4E2D</li></ul><h3 id="extensionclassloader\u2014\u2014\u6269\u5C55\u7C7B\u52A0\u8F7D\u5668" tabindex="-1">ExtensionClassLoader\u2014\u2014\u6269\u5C55\u7C7B\u52A0\u8F7D\u5668 <a class="header-anchor" href="#extensionclassloader\u2014\u2014\u6269\u5C55\u7C7B\u52A0\u8F7D\u5668" aria-hidden="true">#</a></h3><p>ExtensionClassLoader\u7528\u4E8E\u52A0\u8F7D\u4E00\u4E9BJDK\u81EA\u5E26\u7684\u4E00\u4E9B\u6807\u51C6\u6269\u5C55\u5E93\uFF0C\u5982swing\u7B49\u7B49\uFF0C\u6B64\u5916ExtensionClassLoader\u4E5F\u662F\u5176SystemClassLoader\u7236\u7C7B\u3002 -ExtensionClassLoader\u52A0\u8F7D\u7684\u7C7B\u4E00\u822C\u5728JAVA_HOME/lib/ext\u4E2D</p><h3 id="systemclassloader\u2014\u2014\u7CFB\u7EDF\u7C7B\u52A0\u8F7D\u5668" tabindex="-1">SystemClassLoader\u2014\u2014\u7CFB\u7EDF\u7C7B\u52A0\u8F7D\u5668 <a class="header-anchor" href="#systemclassloader\u2014\u2014\u7CFB\u7EDF\u7C7B\u52A0\u8F7D\u5668" aria-hidden="true">#</a></h3><p>SystemClassLoader\u662F\u9762\u5411\u7528\u6237\u7684\u7C7B\u52A0\u8F7D\u5668\uFF0C\u7528\u4E8E\u5728JVM\u8FD0\u884CJava\u7A0B\u5E8F\u65F6\u6839\u636Eclasspath\u5BFB\u627E\u5E76\u52A0\u8F7D\u9700\u8981\u8C03\u7528\u7684\u5305\u548C\u5E93\uFF0C\u4E5F\u88AB\u53EB\u505AAppClassLoader\u3002\u8FD9\u4E00\u7C7B\u7684\u7C7B\u52A0\u8F7D\u5668\u53EF\u4EE5\u901A\u8FC7ClassLoader\u63D0\u4F9B\u7684\u9759\u6001\u65B9\u6CD5getSystemClassLoader()\u6765\u83B7\u53D6\u3002</p><h3 id="customclassloader\u2014\u2014\u81EA\u5B9A\u7C7B\u52A0\u8F7D\u5668" tabindex="-1">CustomClassLoader\u2014\u2014\u81EA\u5B9A\u7C7B\u52A0\u8F7D\u5668 <a class="header-anchor" href="#customclassloader\u2014\u2014\u81EA\u5B9A\u7C7B\u52A0\u8F7D\u5668" aria-hidden="true">#</a></h3><p>\u81EA\u5B9A\u7C7B\u52A0\u8F7D\u5668\u5F80\u5F80\u662FAppClassLoader\u7684\u5B50\u7C7B\uFF0C\u6211\u4EEC\u53EF\u4EE5\u901A\u8FC7\u7EE7\u627Fjava.lang.ClassLoader\u6765\u81EA\u884C\u6784\u9020\u7C7B\u52A0\u8F7D\u5668\u3002\u6B64\u5916\u5728\u81EA\u884C\u6784\u9020\u7C7B\u52A0\u8F7D\u5668\u65F6\uFF0C\u4E5F\u53EF\u4EE5\u81EA\u884C\u5236\u5B9A\u7236\u52A0\u8F7D\u5668<code>protected ClassLoader(ClassLoader parent)</code>\uFF0C\u5728\u4E0D\u6307\u5B9A\u7236\u52A0\u8F7D\u5668\u65F6\u9ED8\u8BA4\u7EE7\u627FAppClassLoader\uFF0C\u800C\u6307\u5B9A\u4E3Anull\u5219\u7EE7\u627FBootstrapClassLoader</p><h2 id="classpath" tabindex="-1">CLASSPATH <a class="header-anchor" href="#classpath" aria-hidden="true">#</a></h2><hr><p>CLASSPATH\u662F\u4E00\u7CFB\u5217\u6587\u4EF6\u8DEF\u5F84\u7684\u96C6\u5408\uFF0C\u5728Windows\u4E2D\u7528\u5206\u53F7\u5206\u9694\uFF0C\u5B83\u6307\u793A\u4E86AppClassLoader\u8981\u4ECE\u54EA\u4E9B\u8DEF\u5F84\u91CC\u641C\u7D22\u9700\u8981\u8C03\u7528\u7684\u7C7B\u6587\u4EF6\u3002CLASSPATH\u6709\u591A\u79CD\u8BBE\u7F6E\u65B9\u5F0F\uFF1A</p><ul><li>\u76F4\u63A5\u8BBE\u7F6E\u7CFB\u7EDF\u73AF\u5883\u53D8\u91CFCLASSPATH\uFF0C\u8003\u8651\u5230\u73B0\u5B9E\u4E2D\u5F80\u5F80\u548C\u4E0D\u540C\u9700\u6C42\u6302\u94A9\uFF0C\u4E00\u822C\u4E0D\u5EFA\u8BAE\u8FD9\u4E48\u505A</li><li>\u5728\u542F\u52A8JVM\u65F6\u4F20\u5165CLASSPATH\u53C2\u6570\uFF0C\u5982<code>java -cp .;xxx</code></li><li>\u5728\u4E0D\u4F20\u5165CLASSPATH\u53C2\u6570\u65F6\uFF0CCLASSPATH\u9ED8\u8BA4\u4E3A&quot;.&quot;\uFF0C\u5373\u5F53\u524D\u76EE\u5F55</li></ul><p>\u628AJVM\u7684\u6838\u5FC3\u5E93\u4F20\u5165CLASSPATH\u662F<strong>\u4E0D\u5FC5\u8981</strong>\u7684\u884C\u4E3A\uFF0C\u56E0\u4E3A\u53CC\u4EB2\u59D4\u6D3E\u673A\u5236\uFF0C\u8FD9\u4E9B\u5E93\u4F9D\u8D56\u4E8EBootstrapClassLoader\u52A0\u8F7D\uFF0C\u800CCLASSPATH\u4EC5\u4EC5\u4E3AAppClassLoader\u8D1F\u8D23</p><h3 id="jar\u5305" tabindex="-1">jar\u5305 <a class="header-anchor" href="#jar\u5305" aria-hidden="true">#</a></h3><p>jar\u672C\u8D28\u4E0A\u662F\u4E00\u4E2A\u53EF\u4EE5\u4F5C\u4E3A\u76EE\u5F55\u7684\u538B\u7F29\u5305\uFF0C\u5728\u4F20\u5165\u5927\u89C4\u6A21\u7684\u7B2C\u4E09\u65B9\u7C7B\u65F6\u53EF\u4EE5\u901A\u8FC7jar\u5305\u6765\u7B80\u5316\u64CD\u4F5C</p><p>\u5F53\u6211\u4EEC\u8F93\u5165<code>java -cp .;./xxx.jar</code>\u65F6\uFF0CclassLoader\u5C31\u4F1A\u8BD5\u56FE\u5728\u5F53\u524D\u76EE\u5F55\u4E0B\u7684xxx.jar\u4E2D\u53BB\u5BFB\u627E\u9700\u8981\u7684\u7C7B\u6587\u4EF6</p><h2 id="\u53CC\u4EB2\u59D4\u6D3E\u673A\u5236\uFF08parent-\uFF09" tabindex="-1">\u53CC\u4EB2\u59D4\u6D3E\u673A\u5236\uFF08parent-\uFF09 <a class="header-anchor" href="#\u53CC\u4EB2\u59D4\u6D3E\u673A\u5236\uFF08parent-\uFF09" aria-hidden="true">#</a></h2><hr><p>\u5728JVM\u52A0\u8F7D\u4E00\u4E2A\u65B0\u7C7B\u65F6\uFF0C\u4F1A\u6839\u636E\u4E00\u4E2A\u4F18\u5148\u7EA7\u9010\u4E2A\u8C03\u7528\u7C7B\u52A0\u8F7D\u5668\uFF0C\u5728\u7C7B\u52A0\u8F7D\u5668\u63A5\u6536\u5230\u52A0\u8F7D\u7C7B\u7684\u8BF7\u6C42\u65F6\uFF0C\u4E0D\u4F1A\u5728\u5176\u5BF9\u5E94\u8DEF\u5F84\u4E0B\u641C\u5BFB\u8BE5\u7C7B\u65F6\uFF0C\u800C\u662F\u5148\u5C06\u8BF7\u6C42\u59D4\u6258\u7ED9\u5176\u7236\u7C7B\uFF0C\u53EA\u6709\u5728\u5176\u7236\u7C7B\u65E0\u6CD5\u52A0\u8F7D\u8BE5\u7C7B\u65F6\u624D\u4F1A\u8BD5\u56FE\u4EB2\u81EA\u52A0\u8F7D\u3002</p><p>\u5728\u7A0B\u5E8F\u8FD0\u884C\u65F6\uFF0C\u7C7B\u52A0\u8F7D\u5668\u5F80\u5F80\u6309\u7167CustomClassLoader-&gt;AppClassLoader-&gt;ExtensionClassLoader-&gt;BootstrapClassLoader\u7684\u987A\u5E8F\u8FDB\u884C\u59D4\u6D3E\uFF0C\u5373</p><ul><li>BootstrapClassLoader\u9996\u5148\u5C1D\u8BD5\u5728JAVA_HOME/lib\u4E2D\u5BFB\u627E\u5BF9\u5E94\u7C7B\uFF0C\u5F53BootstrapClassLoader\u65E0\u6CD5\u5728\u8DEF\u5F84\u4E0B\u627E\u5230\u7C7B\u65F6\uFF0C\u5411\u56DE\u59D4\u6D3E\u7ED9ExtensionClassLoader</li><li>ExtensionClassLoader\u5C1D\u8BD5\u5728JAVA_HOME/lib/ext\u4E2D\u5BFB\u627E\u5BF9\u5E94\u7C7B\uFF0C\u5F53ExtensionClassLoader\u65E0\u6CD5\u5728\u8DEF\u5F84\u4E0B\u627E\u5230\u7C7B\u65F6\uFF0C\u5411\u56DE\u59D4\u6D3E\u7ED9AppClassLoader</li><li>AppClassLoader\u5C1D\u8BD5\u5728#CLASSPATH\u4E2D\u5BFB\u627E\u5BF9\u5E94\u7C7B\uFF0C\u5F53AppClassLoader\u65E0\u6CD5\u5728\u8DEF\u5F84\u4E0B\u627E\u5230\u7C7B\u65F6\uFF0C\u5411\u56DE\u59D4\u6D3E\u7ED9CustomClassLoader\uFF08\u5982\u679C\u6709\uFF09\u6216\u62A5\u9519</li></ul><p>\u91C7\u7528\u53CC\u4EB2\u59D4\u6D3E\u4FDD\u8BC1\u4E86\u7C7B\u662F\u81EA\u9876\u800C\u4E0B\u9010\u7EA7\u5C1D\u8BD5\u52A0\u8F7D\u7684\uFF0C\u53EF\u4EE5\u907F\u514D\u7C7B\u7684\u91CD\u590D\u52A0\u8F7D\uFF0C\u7236\u52A0\u8F7D\u5668\u5728\u641C\u5BFB\u5230\u5BF9\u5E94\u7C7B\u540E\u53EF\u4EE5\u76F4\u63A5\u8C03\u7528\u3002\u6B64\u5916\u53EF\u4EE5\u4FDD\u8BC1\u4F18\u5148\u8C03\u7528JDK\u81EA\u8EAB\u7684\u5185\u90E8\u5E93\uFF0C\u9632\u6B62\u7528\u6237\u81EA\u5B9A\u4E49\u7684\u6838\u5FC3\u5E93\u88AB\u6076\u610F\u8C03\u7528\u3002</p><p>\u6B64\u5916\u7531\u4E8E\u7EE7\u627F\u5173\u7CFB\uFF0C\u5B50\u7C7B\u52A0\u8F7D\u5668\u53EF\u4EE5\u8BBF\u95EE\u7236\u7C7B\u52A0\u8F7D\u5668\u52A0\u8F7D\u7684\u7C7B\uFF08\u5982JDK\u6838\u5FC3\u5185\u90E8\u5E93\u7B49\uFF09\uFF0C\u800C\u53CD\u4E4B\u5219\u4E0D\u7136\uFF0C\u4FDD\u8BC1\u4E86\u5185\u90E8\u5E93\u5BF9\u4E8E\u7A0B\u5E8F\u7684\u53EF\u89C1\u6027\uFF0C\u6362\u53E5\u8BDD\u8BF4\u5373\u5B50\u7C7B\u52A0\u8F7D\u5668\u52A0\u8F7D\u7684\u7C7B\u53EF\u4EE5\u8BBF\u95EE\u7236\u7C7B\u52A0\u8F7D\u5668\u52A0\u8F7D\u7684\u7C7B\uFF0C\u800C\u53CD\u6B63\u5219\u4E0D\u80FD</p><h3 id="\u7F3A\u9677" tabindex="-1">\u7F3A\u9677 <a class="header-anchor" href="#\u7F3A\u9677" aria-hidden="true">#</a></h3><p>JDK\u7684\u6838\u5FC3\u5185\u90E8\u7C7B\u63D0\u4F9B\u4E86\u591A\u4E2ASPI\uFF08Service Provider Interface,\u670D\u52A1\u63D0\u4F9B\u8005\u63A5\u53E3\uFF09\uFF0C\u8FD9\u4E9B\u7C7B\u5F80\u5F80\u9700\u8981\u7B2C\u4E09\u65B9\u7C7B\u6765<strong>\u5B9E\u73B0\u63A5\u53E3</strong>\uFF0C\u6700\u5178\u578B\u7684\u4F8B\u5B50\u5C31\u662F\u5728JDBC\u4E2D\u6211\u4EEC\u9700\u8981\u901A\u8FC7java.sql.driver\u7684DriverManager\u6765\u6CE8\u518C\u9A71\u52A8\uFF0C\u800Cjava.sql.driver\u662F\u7531BootstrapClassLoader\u52A0\u8F7D\u7684\uFF0C\u5B9E\u73B0\u8BE5\u65B9\u6CD5\u7684com.mysql.jdbc.Driver\u5219\u662F\u901A\u8FC7AppClassLoader\u52A0\u8F7D\u7684\uFF0C\u4E3A\u4E86\u8BA9BootstrapClassLoader\u53BB#CLASSPATH\u4E2D\u52A0\u8F7D\u7B2C\u4E09\u65B9\u7C7B\u7684\u65B9\u6CD5\uFF0C\u6211\u4EEC\u9700\u8981\u901A\u8FC7<strong>ContextClassLoader\u2014\u2014\u4E0A\u4E0B\u6587\u52A0\u8F7D\u5668</strong>\u548CClass.forName\u6765\u5B9E\u73B0\u3002</p><p><code>Thread.currentThread().setContextClassLoader(this.loader)</code>\u53EF\u4EE5\u5C06\u5F53\u524D\u7C7B\u7684\u7C7B\u52A0\u8F7D\u5668\u5B58\u50A8\u81F3\u4E0A\u4E0B\u6587\u52A0\u8F7D\u5668\u4E2D\uFF0C\u5E76\u5728\u9700\u8981\u7684\u65F6\u5019\u901A\u8FC7<code>Thread.currentThread().getContextClassLoader()</code>\u8FD4\u56DE\u50A8\u5B58\u7684\u7C7B\u52A0\u8F7D\u5668\u3002</p><p>\u800CClass.forName()\u6709\u4E00\u4E2A\u591A\u53C2\u6570\u7248\u672C\u4E3A\uFF1A</p><div class="language- line-numbers-mode"><button title="Copy Code" class="copy"></button><span class="lang"></span><pre class="shiki"><code><span class="line"><span style="color:#A6ACCD;">Class&lt;?&gt; forName(String name, boolean initialize, ClassLoader cl)</span></span>
<span class="line"><span style="color:#A6ACCD;"></span></span></code></pre><div class="line-numbers-wrapper"><span class="line-number">1</span><br></div></div><p>\u53EF\u4EE5\u901A\u8FC7\u6307\u5B9AclassLoader\u6765\u8C03\u7528\u6307\u5B9A\u7684classLoader\u89E3\u6790\u5F53\u524D\u7C7B</p><p>\u90A3\u4E48\u6211\u4EEC\u5C31\u53EF\u4EE5\u5728\u7236\u7EA7\u7C7B\u52A0\u8F7D\u5668\u52A0\u8F7D\u7684\u7C7B\u7684\u4EE3\u7801\u4E2D\u901A\u8FC7\u4E0A\u4E0B\u6587\u52A0\u8F7D\u5668\u6765\u8C03\u7528\u5B50\u7EA7\u7C7B\u52A0\u8F7D\u5668\uFF0C\u5E76\u7528\u5B50\u7EA7\u7C7B\u52A0\u8F7D\u5668\u6765\u89E3\u6790\u5B9E\u73B0\u8BE5\u63A5\u53E3\u7684\u7B2C\u4E09\u65B9\u7C7B\uFF0C\u4ECE\u800C\u89C4\u907F\u53CC\u4EB2\u59D4\u6D3E\u673A\u5236\u3002</p><h2 id="\u5E38\u91CF\u6C60" tabindex="-1">\u5E38\u91CF\u6C60 <a class="header-anchor" href="#\u5E38\u91CF\u6C60" aria-hidden="true">#</a></h2><hr><p>\u5E38\u91CF\u6C60\u662FJVM\u4E2D\u7684\u4E00\u5757<strong>\u9759\u6001\u5185\u5B58\u7A7A\u95F4</strong>\uFF0C\u7F16\u8BD1\u5668\u5728\u5C06\u6E90\u7801\u7F16\u8BD1\u4E3AClass\u6587\u4EF6\u540E\uFF0C\u4E5F\u5C06<strong>\u5B57\u9762\u91CF</strong>\u548C<strong>\u7B26\u53F7\u5F15\u7528</strong>\u4EE5\u6307\u9488\u94FE\u63A5\u7684\u5F62\u5F0F\u5B58\u5165<strong>\u5E38\u91CF\u6C60</strong>\u4E2D</p><ul><li><strong>\u5B57\u9762\u91CF</strong>\u5305\u62EC\u4E86 <ul><li>\u6587\u672C\u5B57\u9762\u91CF\uFF1A\u5982String s=&quot;123&quot;\u8FD9\u79CD\u5B57\u9762\u91CF\u8D4B\u503C</li><li>final\u7C7B\u578B\u7684\u6210\u5458\u53D8\u91CF</li></ul></li><li><strong>\u7B26\u53F7\u5F15\u7528</strong>\u5305\u62EC\u4E86 <ul><li>\u7C7B\u7684\u5168\u9650\u5B9A\u540D\uFF0C\u5C06Java\u5305\u547D\u540D\u683C\u5F0F\u4E2D\u7684xxx.xxx.xxx\u66FF\u6362\u4E3Axxx/xxx/xxx\u7684\u8DEF\u5F84\u683C\u5F0F</li><li>\u5B57\u6BB5\u540D\uFF0C\u5305\u62EC\u7C7B\u540D\u79F0\u3001\u6E90\u6587\u4EF6\u540D\u3001\u53D8\u91CF\u540D\u7B49\u7B49</li></ul></li></ul><p>\u5728Java\u7A0B\u5E8F\u8FD0\u884C\u65F6\uFF0C\u7531\u4E8EJava\u662F<strong>\u540E\u671F\u7ED1\u5B9A/\u8FD0\u884C\u65F6\u7ED1\u5B9A</strong>\u7684\uFF0C\u5373\u9762\u5411\u5BF9\u8C61\u7A0B\u5E8F\u5728\u7F16\u8BD1\u65F6\u4E0D\u9884\u5148\u89E3\u6790\u65B9\u6CD5\uFF0C\u800C\u662F\u5728\u8FD0\u884C\u65F6\u518D\u53BB\u89E3\u6790\uFF0C\u8FD9\u65F6\u5019\u5C31\u4F9D\u8D56\u4E8E\u5E38\u91CF\u6C60\u4E2D\u7684\u5B57\u6BB5\u6765\u5BFB\u627E\u65B9\u6CD5</p><p>JDK\u81EA\u5E26\u4E86\u4E00\u4E2A\u53CD\u6C47\u7F16\u5DE5\u5177\u2014\u2014javap\uFF0C\u53EF\u4EE5\u5E2E\u52A9\u6211\u4EEC\u5206\u6790Class\u5BF9\u8C61\u7684\u6784\u6210</p><div class="language- line-numbers-mode"><button title="Copy Code" class="copy"></button><span class="lang"></span><pre class="shiki"><code><span class="line"><span style="color:#A6ACCD;">javap</span></span>
<span class="line"><span style="color:#A6ACCD;">\u7528\u6CD5: javap &lt;options&gt; &lt;classes&gt;</span></span>
<span class="line"><span style="color:#A6ACCD;">\u5176\u4E2D, \u53EF\u80FD\u7684\u9009\u9879\u5305\u62EC:</span></span>
<span class="line"><span style="color:#A6ACCD;">  --help -help -h -?               \u8F93\u51FA\u6B64\u5E2E\u52A9\u6D88\u606F</span></span>
<span class="line"><span style="color:#A6ACCD;">  -version                         \u7248\u672C\u4FE1\u606F</span></span>
<span class="line"><span style="color:#A6ACCD;">  -v  -verbose                     \u8F93\u51FA\u9644\u52A0\u4FE1\u606F</span></span>
<span class="line"><span style="color:#A6ACCD;">  -l                               \u8F93\u51FA\u884C\u53F7\u548C\u672C\u5730\u53D8\u91CF\u8868</span></span>
<span class="line"><span style="color:#A6ACCD;">  -public                          \u4EC5\u663E\u793A\u516C\u5171\u7C7B\u548C\u6210\u5458</span></span>
<span class="line"><span style="color:#A6ACCD;">  -protected                       \u663E\u793A\u53D7\u4FDD\u62A4\u7684/\u516C\u5171\u7C7B\u548C\u6210\u5458</span></span>
<span class="line"><span style="color:#A6ACCD;">  -package                         \u663E\u793A\u7A0B\u5E8F\u5305/\u53D7\u4FDD\u62A4\u7684/\u516C\u5171\u7C7B</span></span>
<span class="line"><span style="color:#A6ACCD;">                                   \u548C\u6210\u5458 (\u9ED8\u8BA4)</span></span>
<span class="line"><span style="color:#A6ACCD;">  -p  -private                     \u663E\u793A\u6240\u6709\u7C7B\u548C\u6210\u5458</span></span>
<span class="line"><span style="color:#A6ACCD;">  -c                               \u5BF9\u4EE3\u7801\u8FDB\u884C\u53CD\u6C47\u7F16</span></span>
<span class="line"><span style="color:#A6ACCD;">  -s                               \u8F93\u51FA\u5185\u90E8\u7C7B\u578B\u7B7E\u540D</span></span>
<span class="line"><span style="color:#A6ACCD;">  -sysinfo                         \u663E\u793A\u6B63\u5728\u5904\u7406\u7684\u7C7B\u7684</span></span>
<span class="line"><span style="color:#A6ACCD;">                                   \u7CFB\u7EDF\u4FE1\u606F\uFF08\u8DEF\u5F84\u3001\u5927\u5C0F\u3001\u65E5\u671F\u3001SHA-256 \u6563\u5217\uFF09</span></span>
<span class="line"><span style="color:#A6ACCD;">  -constants                       \u663E\u793A\u6700\u7EC8\u5E38\u91CF</span></span>
<span class="line"><span style="color:#A6ACCD;">  --module &lt;\u6A21\u5757&gt;  -m &lt;\u6A21\u5757&gt;       \u6307\u5B9A\u5305\u542B\u8981\u53CD\u6C47\u7F16\u7684\u7C7B\u7684\u6A21\u5757</span></span>
<span class="line"><span style="color:#A6ACCD;">  -J&lt;vm-option&gt;                    \u6307\u5B9A VM \u9009\u9879</span></span>
<span class="line"><span style="color:#A6ACCD;">  --module-path &lt;\u8DEF\u5F84&gt;             \u6307\u5B9A\u67E5\u627E\u5E94\u7528\u7A0B\u5E8F\u6A21\u5757\u7684\u4F4D\u7F6E</span></span>
<span class="line"><span style="color:#A6ACCD;">  --system &lt;jdk&gt;                   \u6307\u5B9A\u67E5\u627E\u7CFB\u7EDF\u6A21\u5757\u7684\u4F4D\u7F6E</span></span>
<span class="line"><span style="color:#A6ACCD;">  --class-path &lt;\u8DEF\u5F84&gt;              \u6307\u5B9A\u67E5\u627E\u7528\u6237\u7C7B\u6587\u4EF6\u7684\u4F4D\u7F6E</span></span>
<span class="line"><span style="color:#A6ACCD;">  -classpath &lt;\u8DEF\u5F84&gt;                \u6307\u5B9A\u67E5\u627E\u7528\u6237\u7C7B\u6587\u4EF6\u7684\u4F4D\u7F6E</span></span>
<span class="line"><span style="color:#A6ACCD;">  -cp &lt;\u8DEF\u5F84&gt;                       \u6307\u5B9A\u67E5\u627E\u7528\u6237\u7C7B\u6587\u4EF6\u7684\u4F4D\u7F6E</span></span>
<span class="line"><span style="color:#A6ACCD;">  -bootclasspath &lt;\u8DEF\u5F84&gt;            \u8986\u76D6\u5F15\u5BFC\u7C7B\u6587\u4EF6\u7684\u4F4D\u7F6E</span></span>
<span class="line"><span style="color:#A6ACCD;">  --multi-release &lt;version&gt;        \u6307\u5B9A\u8981\u5728\u591A\u53D1\u884C\u7248 JAR \u6587\u4EF6\u4E2D\u4F7F\u7528\u7684\u7248\u672C</span></span>
<span class="line"><span style="color:#A6ACCD;">GNU \u6837\u5F0F\u7684\u9009\u9879\u53EF\u4F7F\u7528 = (\u800C\u975E\u7A7A\u767D) \u6765\u5206\u9694\u9009\u9879\u540D\u79F0</span></span>
<span class="line"><span style="color:#A6ACCD;">\u53CA\u5176\u503C\u3002</span></span>
<span class="line"><span style="color:#A6ACCD;"></span></span>
<span class="line"><span style="color:#A6ACCD;">\u6BCF\u4E2A\u7C7B\u53EF\u7531\u5176\u6587\u4EF6\u540D, URL \u6216\u5176</span></span>
<span class="line"><span style="color:#A6ACCD;">\u5168\u9650\u5B9A\u7C7B\u540D\u6307\u5B9A\u3002\u793A\u4F8B:</span></span>
<span class="line"><span style="color:#A6ACCD;">   path/to/MyClass.class</span></span>
<span class="line"><span style="color:#A6ACCD;">   jar:file:///path/to/MyJar.jar!/mypkg/MyClass.class</span></span>
<span class="line"><span style="color:#A6ACCD;">   java.lang.Object</span></span>
<span class="line"><span style="color:#A6ACCD;"></span></span></code></pre><div class="line-numbers-wrapper"><span class="line-number">1</span><br><span class="line-number">2</span><br><span class="line-number">3</span><br><span class="line-number">4</span><br><span class="line-number">5</span><br><span class="line-number">6</span><br><span class="line-number">7</span><br><span class="line-number">8</span><br><span class="line-number">9</span><br><span class="line-number">10</span><br><span class="line-number">11</span><br><span class="line-number">12</span><br><span class="line-number">13</span><br><span class="line-number">14</span><br><span class="line-number">15</span><br><span class="line-number">16</span><br><span class="line-number">17</span><br><span class="line-number">18</span><br><span class="line-number">19</span><br><span class="line-number">20</span><br><span class="line-number">21</span><br><span class="line-number">22</span><br><span class="line-number">23</span><br><span class="line-number">24</span><br><span class="line-number">25</span><br><span class="line-number">26</span><br><span class="line-number">27</span><br><span class="line-number">28</span><br><span class="line-number">29</span><br><span class="line-number">30</span><br><span class="line-number">31</span><br><span class="line-number">32</span><br><span class="line-number">33</span><br><span class="line-number">34</span><br></div></div><p>\u6211\u4EEC\u73B0\u5728\u6709\u4E00\u4E2AJava\u7684helloworld\u7A0B\u5E8F\uFF0C\u5E76\u901A\u8FC7JDK\u63D0\u4F9B\u7684<code>javap</code>\u5BF9\u5176\u8FDB\u884C\u53CD\u6C47\u7F16</p><div class="language-Java line-numbers-mode"><button title="Copy Code" class="copy"></button><span class="lang">Java</span><pre class="shiki"><code><span class="line"><span style="color:#676E95;">/*Main.java*/</span></span>
<span class="line"><span style="color:#C792EA;">public</span><span style="color:#A6ACCD;"> </span><span style="color:#C792EA;">class</span><span style="color:#A6ACCD;"> </span><span style="color:#FFCB6B;">Main</span><span style="color:#A6ACCD;"> </span><span style="color:#89DDFF;">{</span></span>
<span class="line"><span style="color:#A6ACCD;">    </span><span style="color:#C792EA;">public</span><span style="color:#A6ACCD;"> </span><span style="color:#C792EA;">static</span><span style="color:#A6ACCD;"> </span><span style="color:#C792EA;">void</span><span style="color:#A6ACCD;"> </span><span style="color:#82AAFF;">main</span><span style="color:#89DDFF;">(</span><span style="color:#C792EA;">String</span><span style="color:#89DDFF;">[]</span><span style="color:#A6ACCD;"> </span><span style="color:#A6ACCD;">args</span><span style="color:#89DDFF;">)</span><span style="color:#A6ACCD;"> </span><span style="color:#89DDFF;">{</span></span>
<span class="line"><span style="color:#A6ACCD;">        System</span><span style="color:#89DDFF;">.</span><span style="color:#A6ACCD;">out</span><span style="color:#89DDFF;">.</span><span style="color:#82AAFF;">println</span><span style="color:#89DDFF;">(</span><span style="color:#89DDFF;">&quot;</span><span style="color:#C3E88D;">Hello world!</span><span style="color:#89DDFF;">&quot;</span><span style="color:#89DDFF;">);</span></span>
<span class="line"><span style="color:#A6ACCD;">    </span><span style="color:#89DDFF;">}</span></span>
<span class="line"><span style="color:#89DDFF;">}</span></span>
<span class="line"></span></code></pre><div class="line-numbers-wrapper"><span class="line-number">1</span><br><span class="line-number">2</span><br><span class="line-number">3</span><br><span class="line-number">4</span><br><span class="line-number">5</span><br><span class="line-number">6</span><br></div></div><div class="language- line-numbers-mode"><button title="Copy Code" class="copy"></button><span class="lang"></span><pre class="shiki"><code><span class="line"><span style="color:#A6ACCD;">&gt; javap -c Main.class</span></span>
<span class="line"><span style="color:#A6ACCD;">Compiled from &quot;Main.java&quot;</span></span>
<span class="line"><span style="color:#A6ACCD;">public class Main {</span></span>
<span class="line"><span style="color:#A6ACCD;">  public Main();</span></span>
<span class="line"><span style="color:#A6ACCD;">    Code:</span></span>
<span class="line"><span style="color:#A6ACCD;">       0: aload_0</span></span>
<span class="line"><span style="color:#A6ACCD;">       1: invokespecial #1                  // Method java/lang/Object.&quot;&lt;init&gt;&quot;:()V</span></span>
<span class="line"><span style="color:#A6ACCD;">       4: return</span></span>
<span class="line"><span style="color:#A6ACCD;"></span></span>
<span class="line"><span style="color:#A6ACCD;">  public static void main(java.lang.String[]);</span></span>
<span class="line"><span style="color:#A6ACCD;">    Code:</span></span>
<span class="line"><span style="color:#A6ACCD;">       0: getstatic     #7                  // Field java/lang/System.out:Ljava/io/PrintStream;</span></span>
<span class="line"><span style="color:#A6ACCD;">       3: ldc           #13                 // String Hello world!</span></span>
<span class="line"><span style="color:#A6ACCD;">       5: invokevirtual #15                 // Method java/io/PrintStream.println:(Ljava/lang/String;)V</span></span>
<span class="line"><span style="color:#A6ACCD;">       8: return</span></span>
<span class="line"><span style="color:#A6ACCD;">}</span></span>
<span class="line"><span style="color:#A6ACCD;"></span></span></code></pre><div class="line-numbers-wrapper"><span class="line-number">1</span><br><span class="line-number">2</span><br><span class="line-number">3</span><br><span class="line-number">4</span><br><span class="line-number">5</span><br><span class="line-number">6</span><br><span class="line-number">7</span><br><span class="line-number">8</span><br><span class="line-number">9</span><br><span class="line-number">10</span><br><span class="line-number">11</span><br><span class="line-number">12</span><br><span class="line-number">13</span><br><span class="line-number">14</span><br><span class="line-number">15</span><br><span class="line-number">16</span><br></div></div><p>\u4ECE\u8FD9\u91CC\u53EF\u4EE5\u770B\u51FA\u7F16\u8BD1\u5668\u4E3AMain\u7C7B\u81EA\u52A8\u8865\u5168\u4E86\u96F6\u53C2\u6784\u9020\u5668\uFF08public Main\uFF09</p><p>\u6211\u4EEC\u5C06\u7A0B\u5E8F\u4FEE\u6539\uFF0C\u53EF\u4EE5\u89C2\u5BDF\u5230\u5176\u4E0D\u540C\u7C7B\u578B\u7684\u53D8\u91CF\u7684\u5B58\u50A8\u5F62\u5F0F\uFF0C\u5E76\u5C06\u53CD\u6C47\u7F16\u6307\u4EE4\u4FEE\u6539\u4E3A<code>javap -c -v Main.Class</code></p><ul><li>-v -verbose\u53EF\u4EE5\u663E\u793A\u8BE5Class\u5BF9\u8C61\u7684\u5E38\u91CF\u6C60</li></ul><div class="language-Java line-numbers-mode"><button title="Copy Code" class="copy"></button><span class="lang">Java</span><pre class="shiki"><code><span class="line"><span style="color:#C792EA;">public</span><span style="color:#A6ACCD;"> </span><span style="color:#C792EA;">class</span><span style="color:#A6ACCD;"> </span><span style="color:#FFCB6B;">Main</span><span style="color:#A6ACCD;"> </span><span style="color:#89DDFF;">{</span></span>
<span class="line"><span style="color:#A6ACCD;">    </span><span style="color:#C792EA;">final</span><span style="color:#A6ACCD;"> </span><span style="color:#C792EA;">int</span><span style="color:#A6ACCD;"> i</span><span style="color:#89DDFF;">=</span><span style="color:#F78C6C;">111</span><span style="color:#89DDFF;">;</span></span>
<span class="line"><span style="color:#A6ACCD;">    </span><span style="color:#C792EA;">static</span><span style="color:#A6ACCD;"> </span><span style="color:#C792EA;">int</span><span style="color:#A6ACCD;"> test</span><span style="color:#89DDFF;">=</span><span style="color:#F78C6C;">5</span><span style="color:#89DDFF;">;</span></span>
<span class="line"><span style="color:#A6ACCD;">    </span><span style="color:#C792EA;">public</span><span style="color:#A6ACCD;"> </span><span style="color:#C792EA;">static</span><span style="color:#A6ACCD;"> </span><span style="color:#C792EA;">void</span><span style="color:#A6ACCD;"> </span><span style="color:#82AAFF;">main</span><span style="color:#89DDFF;">(</span><span style="color:#C792EA;">String</span><span style="color:#89DDFF;">[]</span><span style="color:#A6ACCD;"> </span><span style="color:#A6ACCD;">args</span><span style="color:#89DDFF;">)</span><span style="color:#A6ACCD;"> </span><span style="color:#89DDFF;">{</span></span>
<span class="line"><span style="color:#A6ACCD;">        System</span><span style="color:#89DDFF;">.</span><span style="color:#A6ACCD;">out</span><span style="color:#89DDFF;">.</span><span style="color:#82AAFF;">println</span><span style="color:#89DDFF;">(</span><span style="color:#89DDFF;">&quot;</span><span style="color:#C3E88D;">Hello world!</span><span style="color:#89DDFF;">&quot;</span><span style="color:#89DDFF;">);</span></span>
<span class="line"><span style="color:#A6ACCD;">        </span><span style="color:#C792EA;">String</span><span style="color:#A6ACCD;"> s</span><span style="color:#89DDFF;">=</span><span style="color:#89DDFF;">&quot;</span><span style="color:#C3E88D;">123</span><span style="color:#89DDFF;">&quot;</span><span style="color:#89DDFF;">;</span></span>
<span class="line"><span style="color:#A6ACCD;">        </span><span style="color:#C792EA;">int</span><span style="color:#A6ACCD;"> j</span><span style="color:#89DDFF;">=</span><span style="color:#F78C6C;">10</span><span style="color:#89DDFF;">;</span></span>
<span class="line"><span style="color:#A6ACCD;">    </span><span style="color:#89DDFF;">}</span></span>
<span class="line"><span style="color:#89DDFF;">}</span></span>
<span class="line"></span></code></pre><div class="line-numbers-wrapper"><span class="line-number">1</span><br><span class="line-number">2</span><br><span class="line-number">3</span><br><span class="line-number">4</span><br><span class="line-number">5</span><br><span class="line-number">6</span><br><span class="line-number">7</span><br><span class="line-number">8</span><br><span class="line-number">9</span><br></div></div><div class="language- line-numbers-mode"><button title="Copy Code" class="copy"></button><span class="lang"></span><pre class="shiki"><code><span class="line"><span style="color:#A6ACCD;">&gt; javap -c -v Main.class</span></span>
<span class="line"><span style="color:#A6ACCD;">//\u8FD9\u91CC\u662F\u7A0B\u5E8F\u7684\u4E00\u4E9B\u5143\u6570\u636E\uFF0C\u5305\u62EC\u4FEE\u6539\u65E5\u671F\u3001\u957F\u5EA6\u3001\u6E90\u6587\u4EF6\u7B49\u7B49</span></span>
<span class="line"><span style="color:#A6ACCD;">  Last modified 2023\u5E743\u670811\u65E5; size 732 bytes</span></span>
<span class="line"><span style="color:#A6ACCD;">  SHA-256 checksum 3f5aabfe4ea8c85ce7f6f91b4b97154a5440190b09f2ece92c4690f40ffd00e2</span></span>
<span class="line"><span style="color:#A6ACCD;">  Compiled from &quot;Main.java&quot;</span></span>
<span class="line"><span style="color:#A6ACCD;">public class Main</span></span>
<span class="line"><span style="color:#A6ACCD;">  minor version: 0</span></span>
<span class="line"><span style="color:#A6ACCD;">  major version: 63</span></span>
<span class="line"><span style="color:#A6ACCD;">  flags: (0x0021) ACC_PUBLIC, ACC_SUPER</span></span>
<span class="line"><span style="color:#A6ACCD;">  this_class: #8                          // Main</span></span>
<span class="line"><span style="color:#A6ACCD;">  super_class: #2                         // java/lang/Object</span></span>
<span class="line"><span style="color:#A6ACCD;">  interfaces: 0, fields: 2, methods: 3, attributes: 1</span></span>
<span class="line"><span style="color:#A6ACCD;"></span></span>
<span class="line"><span style="color:#A6ACCD;">//\u5E38\u91CF\u6C60 </span></span>
<span class="line"><span style="color:#A6ACCD;">Constant pool:</span></span>
<span class="line"><span style="color:#A6ACCD;">   #1 = Methodref          #2.#3          // java/lang/Object.&quot;&lt;init&gt;&quot;:()V</span></span>
<span class="line"><span style="color:#A6ACCD;">   #2 = Class              #4             // java/lang/Object</span></span>
<span class="line"><span style="color:#A6ACCD;">   #3 = NameAndType        #5:#6          // &quot;&lt;init&gt;&quot;:()V</span></span>
<span class="line"><span style="color:#A6ACCD;">   #4 = Utf8               java/lang/Object</span></span>
<span class="line"><span style="color:#A6ACCD;">   #5 = Utf8               &lt;init&gt;</span></span>
<span class="line"><span style="color:#A6ACCD;">   #6 = Utf8               ()V</span></span>
<span class="line"><span style="color:#A6ACCD;">   #7 = Fieldref           #8.#9          // Main.i:I</span></span>
<span class="line"><span style="color:#A6ACCD;">   #8 = Class              #10            // Main</span></span>
<span class="line"><span style="color:#A6ACCD;">   #9 = NameAndType        #11:#12        // i:I</span></span>
<span class="line"><span style="color:#A6ACCD;">  #10 = Utf8               Main</span></span>
<span class="line"><span style="color:#A6ACCD;">  #11 = Utf8               i</span></span>
<span class="line"><span style="color:#A6ACCD;">  #12 = Utf8               I</span></span>
<span class="line"><span style="color:#A6ACCD;">  #13 = Fieldref           #14.#15        // java/lang/System.out:Ljava/io/PrintStream;</span></span>
<span class="line"><span style="color:#A6ACCD;">  #14 = Class              #16            // java/lang/System</span></span>
<span class="line"><span style="color:#A6ACCD;">  #15 = NameAndType        #17:#18        // out:Ljava/io/PrintStream;</span></span>
<span class="line"><span style="color:#A6ACCD;">  #16 = Utf8               java/lang/System</span></span>
<span class="line"><span style="color:#A6ACCD;">  #17 = Utf8               out</span></span>
<span class="line"><span style="color:#A6ACCD;">  #18 = Utf8               Ljava/io/PrintStream;</span></span>
<span class="line"><span style="color:#A6ACCD;">  #19 = String             #20            // Hello world!</span></span>
<span class="line"><span style="color:#A6ACCD;">  #20 = Utf8               Hello world!</span></span>
<span class="line"><span style="color:#A6ACCD;">  #21 = Methodref          #22.#23        // java/io/PrintStream.println:(Ljava/lang/String;)V</span></span>
<span class="line"><span style="color:#A6ACCD;">  #22 = Class              #24            // java/io/PrintStream</span></span>
<span class="line"><span style="color:#A6ACCD;">  #23 = NameAndType        #25:#26        // println:(Ljava/lang/String;)V</span></span>
<span class="line"><span style="color:#A6ACCD;">  #24 = Utf8               java/io/PrintStream</span></span>
<span class="line"><span style="color:#A6ACCD;">  #25 = Utf8               println</span></span>
<span class="line"><span style="color:#A6ACCD;">  #26 = Utf8               (Ljava/lang/String;)V</span></span>
<span class="line"><span style="color:#A6ACCD;">  #27 = String             #28            // 123</span></span>
<span class="line"><span style="color:#A6ACCD;">  #28 = Utf8               123</span></span>
<span class="line"><span style="color:#A6ACCD;">  #29 = Fieldref           #8.#30         // Main.test:I</span></span>
<span class="line"><span style="color:#A6ACCD;">  #30 = NameAndType        #31:#12        // test:I</span></span>
<span class="line"><span style="color:#A6ACCD;">  #31 = Utf8               test</span></span>
<span class="line"><span style="color:#A6ACCD;">  #32 = Utf8               ConstantValue</span></span>
<span class="line"><span style="color:#A6ACCD;">  #33 = Integer            111</span></span>
<span class="line"><span style="color:#A6ACCD;">  #34 = Utf8               Code</span></span>
<span class="line"><span style="color:#A6ACCD;">  #35 = Utf8               LineNumberTable</span></span>
<span class="line"><span style="color:#A6ACCD;">  #36 = Utf8               LocalVariableTable</span></span>
<span class="line"><span style="color:#A6ACCD;">  #37 = Utf8               this</span></span>
<span class="line"><span style="color:#A6ACCD;">  #38 = Utf8               LMain;</span></span>
<span class="line"><span style="color:#A6ACCD;">  #39 = Utf8               main</span></span>
<span class="line"><span style="color:#A6ACCD;">  #40 = Utf8               ([Ljava/lang/String;)V</span></span>
<span class="line"><span style="color:#A6ACCD;">  #41 = Utf8               args</span></span>
<span class="line"><span style="color:#A6ACCD;">  #42 = Utf8               [Ljava/lang/String;</span></span>
<span class="line"><span style="color:#A6ACCD;">  #43 = Utf8               s</span></span>
<span class="line"><span style="color:#A6ACCD;">  #44 = Utf8               Ljava/lang/String;</span></span>
<span class="line"><span style="color:#A6ACCD;">  #45 = Utf8               j</span></span>
<span class="line"><span style="color:#A6ACCD;">  #46 = Utf8               &lt;clinit&gt;</span></span>
<span class="line"><span style="color:#A6ACCD;">  #47 = Utf8               SourceFile</span></span>
<span class="line"><span style="color:#A6ACCD;">  #48 = Utf8               Main.java</span></span>
<span class="line"><span style="color:#A6ACCD;"></span></span>
<span class="line"><span style="color:#A6ACCD;">//\u4EE3\u7801\u5757</span></span>
<span class="line"><span style="color:#A6ACCD;">{</span></span>
<span class="line"><span style="color:#A6ACCD;">  final int i;</span></span>
<span class="line"><span style="color:#A6ACCD;">    descriptor: I</span></span>
<span class="line"><span style="color:#A6ACCD;">    flags: (0x0010) ACC_FINAL</span></span>
<span class="line"><span style="color:#A6ACCD;">    ConstantValue: int 111</span></span>
<span class="line"><span style="color:#A6ACCD;"></span></span>
<span class="line"><span style="color:#A6ACCD;">  static int test;</span></span>
<span class="line"><span style="color:#A6ACCD;">    descriptor: I</span></span>
<span class="line"><span style="color:#A6ACCD;">    flags: (0x0008) ACC_STATIC</span></span>
<span class="line"><span style="color:#A6ACCD;"></span></span>
<span class="line"><span style="color:#A6ACCD;">  public Main();</span></span>
<span class="line"><span style="color:#A6ACCD;">    descriptor: ()V</span></span>
<span class="line"><span style="color:#A6ACCD;">    flags: (0x0001) ACC_PUBLIC</span></span>
<span class="line"><span style="color:#A6ACCD;">    Code:</span></span>
<span class="line"><span style="color:#A6ACCD;">      stack=2, locals=1, args_size=1</span></span>
<span class="line"><span style="color:#A6ACCD;">         0: aload_0</span></span>
<span class="line"><span style="color:#A6ACCD;">         1: invokespecial #1                  // Method java/lang/Object.&quot;&lt;init&gt;&quot;:()V</span></span>
<span class="line"><span style="color:#A6ACCD;">         4: aload_0</span></span>
<span class="line"><span style="color:#A6ACCD;">         5: bipush        111</span></span>
<span class="line"><span style="color:#A6ACCD;">         7: putfield      #7                  // Field i:I</span></span>
<span class="line"><span style="color:#A6ACCD;">        10: return</span></span>
<span class="line"><span style="color:#A6ACCD;">      LineNumberTable:</span></span>
<span class="line"><span style="color:#A6ACCD;">        line 1: 0</span></span>
<span class="line"><span style="color:#A6ACCD;">        line 2: 4</span></span>
<span class="line"><span style="color:#A6ACCD;">      LocalVariableTable:</span></span>
<span class="line"><span style="color:#A6ACCD;">        Start  Length  Slot  Name   Signature</span></span>
<span class="line"><span style="color:#A6ACCD;">            0      11     0  this   LMain;</span></span>
<span class="line"><span style="color:#A6ACCD;"></span></span>
<span class="line"><span style="color:#A6ACCD;">  public static void main(java.lang.String[]);</span></span>
<span class="line"><span style="color:#A6ACCD;">    descriptor: ([Ljava/lang/String;)V</span></span>
<span class="line"><span style="color:#A6ACCD;">    flags: (0x0009) ACC_PUBLIC, ACC_STATIC</span></span>
<span class="line"><span style="color:#A6ACCD;">    Code:</span></span>
<span class="line"><span style="color:#A6ACCD;">      stack=2, locals=3, args_size=1</span></span>
<span class="line"><span style="color:#A6ACCD;">         0: getstatic     #13                 // Field java/lang/System.out:Ljava/io/PrintStream;</span></span>
<span class="line"><span style="color:#A6ACCD;">         3: ldc           #19                 // String Hello world!</span></span>
<span class="line"><span style="color:#A6ACCD;">         5: invokevirtual #21                 // Method java/io/PrintStream.println:(Ljava/lang/String;)V</span></span>
<span class="line"><span style="color:#A6ACCD;">         8: ldc           #27                 // String 123</span></span>
<span class="line"><span style="color:#A6ACCD;">        10: astore_1</span></span>
<span class="line"><span style="color:#A6ACCD;">        11: bipush        10</span></span>
<span class="line"><span style="color:#A6ACCD;">        13: istore_2</span></span>
<span class="line"><span style="color:#A6ACCD;">        14: return</span></span>
<span class="line"><span style="color:#A6ACCD;">      LineNumberTable:</span></span>
<span class="line"><span style="color:#A6ACCD;">        line 5: 0</span></span>
<span class="line"><span style="color:#A6ACCD;">        line 6: 8</span></span>
<span class="line"><span style="color:#A6ACCD;">        line 7: 11</span></span>
<span class="line"><span style="color:#A6ACCD;">        line 8: 14</span></span>
<span class="line"><span style="color:#A6ACCD;">      LocalVariableTable:</span></span>
<span class="line"><span style="color:#A6ACCD;">        Start  Length  Slot  Name   Signature</span></span>
<span class="line"><span style="color:#A6ACCD;">            0      15     0  args   [Ljava/lang/String;</span></span>
<span class="line"><span style="color:#A6ACCD;">           11       4     1     s   Ljava/lang/String;</span></span>
<span class="line"><span style="color:#A6ACCD;">           14       1     2     j   I</span></span>
<span class="line"><span style="color:#A6ACCD;"></span></span>
<span class="line"><span style="color:#A6ACCD;">  static {};</span></span>
<span class="line"><span style="color:#A6ACCD;">    descriptor: ()V</span></span>
<span class="line"><span style="color:#A6ACCD;">    flags: (0x0008) ACC_STATIC</span></span>
<span class="line"><span style="color:#A6ACCD;">    Code:</span></span>
<span class="line"><span style="color:#A6ACCD;">      stack=1, locals=0, args_size=0</span></span>
<span class="line"><span style="color:#A6ACCD;">         0: iconst_5</span></span>
<span class="line"><span style="color:#A6ACCD;">         1: putstatic     #29                 // Field test:I</span></span>
<span class="line"><span style="color:#A6ACCD;">         4: return</span></span>
<span class="line"><span style="color:#A6ACCD;">      LineNumberTable:</span></span>
<span class="line"><span style="color:#A6ACCD;">        line 3: 0</span></span>
<span class="line"><span style="color:#A6ACCD;">}</span></span>
<span class="line"><span style="color:#A6ACCD;">SourceFile: &quot;Main.java&quot;</span></span>
<span class="line"><span style="color:#A6ACCD;"></span></span></code></pre><div class="line-numbers-wrapper"><span class="line-number">1</span><br><span class="line-number">2</span><br><span class="line-number">3</span><br><span class="line-number">4</span><br><span class="line-number">5</span><br><span class="line-number">6</span><br><span class="line-number">7</span><br><span class="line-number">8</span><br><span class="line-number">9</span><br><span class="line-number">10</span><br><span class="line-number">11</span><br><span class="line-number">12</span><br><span class="line-number">13</span><br><span class="line-number">14</span><br><span class="line-number">15</span><br><span class="line-number">16</span><br><span class="line-number">17</span><br><span class="line-number">18</span><br><span class="line-number">19</span><br><span class="line-number">20</span><br><span class="line-number">21</span><br><span class="line-number">22</span><br><span class="line-number">23</span><br><span class="line-number">24</span><br><span class="line-number">25</span><br><span class="line-number">26</span><br><span class="line-number">27</span><br><span class="line-number">28</span><br><span class="line-number">29</span><br><span class="line-number">30</span><br><span class="line-number">31</span><br><span class="line-number">32</span><br><span class="line-number">33</span><br><span class="line-number">34</span><br><span class="line-number">35</span><br><span class="line-number">36</span><br><span class="line-number">37</span><br><span class="line-number">38</span><br><span class="line-number">39</span><br><span class="line-number">40</span><br><span class="line-number">41</span><br><span class="line-number">42</span><br><span class="line-number">43</span><br><span class="line-number">44</span><br><span class="line-number">45</span><br><span class="line-number">46</span><br><span class="line-number">47</span><br><span class="line-number">48</span><br><span class="line-number">49</span><br><span class="line-number">50</span><br><span class="line-number">51</span><br><span class="line-number">52</span><br><span class="line-number">53</span><br><span class="line-number">54</span><br><span class="line-number">55</span><br><span class="line-number">56</span><br><span class="line-number">57</span><br><span class="line-number">58</span><br><span class="line-number">59</span><br><span class="line-number">60</span><br><span class="line-number">61</span><br><span class="line-number">62</span><br><span class="line-number">63</span><br><span class="line-number">64</span><br><span class="line-number">65</span><br><span class="line-number">66</span><br><span class="line-number">67</span><br><span class="line-number">68</span><br><span class="line-number">69</span><br><span class="line-number">70</span><br><span class="line-number">71</span><br><span class="line-number">72</span><br><span class="line-number">73</span><br><span class="line-number">74</span><br><span class="line-number">75</span><br><span class="line-number">76</span><br><span class="line-number">77</span><br><span class="line-number">78</span><br><span class="line-number">79</span><br><span class="line-number">80</span><br><span class="line-number">81</span><br><span class="line-number">82</span><br><span class="line-number">83</span><br><span class="line-number">84</span><br><span class="line-number">85</span><br><span class="line-number">86</span><br><span class="line-number">87</span><br><span class="line-number">88</span><br><span class="line-number">89</span><br><span class="line-number">90</span><br><span class="line-number">91</span><br><span class="line-number">92</span><br><span class="line-number">93</span><br><span class="line-number">94</span><br><span class="line-number">95</span><br><span class="line-number">96</span><br><span class="line-number">97</span><br><span class="line-number">98</span><br><span class="line-number">99</span><br><span class="line-number">100</span><br><span class="line-number">101</span><br><span class="line-number">102</span><br><span class="line-number">103</span><br><span class="line-number">104</span><br><span class="line-number">105</span><br><span class="line-number">106</span><br><span class="line-number">107</span><br><span class="line-number">108</span><br><span class="line-number">109</span><br><span class="line-number">110</span><br><span class="line-number">111</span><br><span class="line-number">112</span><br><span class="line-number">113</span><br><span class="line-number">114</span><br><span class="line-number">115</span><br><span class="line-number">116</span><br><span class="line-number">117</span><br><span class="line-number">118</span><br><span class="line-number">119</span><br><span class="line-number">120</span><br><span class="line-number">121</span><br><span class="line-number">122</span><br><span class="line-number">123</span><br><span class="line-number">124</span><br><span class="line-number">125</span><br><span class="line-number">126</span><br><span class="line-number">127</span><br><span class="line-number">128</span><br><span class="line-number">129</span><br></div></div>`,61),r=[e];function o(c,t,i,C,A,b){return a(),n("div",null,r)}const D=s(p,[["render",o]]);export{y as __pageData,D as default};
